LSDpy/__init__.py
LSDpy/lsdpFunc.py
LSDpy/lsdpy.py
lsdpy-1.0.0.dist-info/licenses/LICENSE
lsdpy-1.0.0.dist-info/METADATA
lsdpy-1.0.0.dist-info/WHEEL
lsdpy-1.0.0.dist-info/entry_points.txt
lsdpy-1.0.0.dist-info/top_level.txt
lsdpy-1.0.0.dist-info/RECORD
